mammos_units/__init__.py
mammos_units/py.typed
mammos_units-0.3.2.dist-info/METADATA
mammos_units-0.3.2.dist-info/WHEEL
mammos_units-0.3.2.dist-info/licenses/LICENSE
mammos_units-0.3.2.dist-info/RECORD
